setup.py
odoo/addons/mail_activity_chatter/CHANGELOG.md
odoo/addons/mail_activity_chatter/README.rst
odoo/addons/mail_activity_chatter/__init__.py
odoo/addons/mail_activity_chatter/__manifest__.py
odoo/addons/mail_activity_chatter/models/__init__.py
odoo/addons/mail_activity_chatter/models/mail_activity.py
odoo/addons/mail_activity_chatter/static/description/icon.png
odoo/addons/mail_activity_chatter/static/src/xml/mail_chatter_buttons.xml
odoo/addons/mail_activity_chatter/views/mail_activity_views.xml
odoo_addon_mail_activity_chatter.egg-info/PKG-INFO
odoo_addon_mail_activity_chatter.egg-info/SOURCES.txt
odoo_addon_mail_activity_chatter.egg-info/dependency_links.txt
odoo_addon_mail_activity_chatter.egg-info/not-zip-safe
odoo_addon_mail_activity_chatter.egg-info/requires.txt
odoo_addon_mail_activity_chatter.egg-info/top_level.txt